{
  "data": [
    {
      "id": 1,
      "name": "Абетка",
      "order": 3,
      "lessons": [
        {
          "words": [
            {

            }
          ]
        },
        {

        }
      ]
    },
    {
      "id": 2,
      "name": "Тварини",
      "order": 2
    },
    {
      "id": 3,
      "name": "Рослини",
      "order": 1
    },
    {
      "id": 4,
      "name": "",
      "order": 4
    },
    {
      "id": 5,
      "name": "",
      "order": 6
    },
    {
      "id": 6,
      "name": "",
      "order": 5
    },
    {
      "id": 7,
      "name": "",
      "order": 7
    }
  ]
}
